src/runner.v
// Отправитель
// cd C:\iverilog\runner                   АНДРЕЙ           
// cd C:\iverilog\runner\Lab5-Cxemota      ЮЛЯ
// iverilog -o ./compiled ./src/runner.v ./src/runner_tb.v ./src/runner_lab.v
// vvp ./compiled 
module runner
(
    output [5:0] led,
    input rstn,
    input sys_clk,
    input t_start,
    input up,
    output cs,
    input miso, 
    output mosi,
    output sclk
);

parameter reg_width = 8;
parameter counter_width = $clog2(reg_width);
parameter reset = 0, idle = 1, load = 2, transact1 = 3, transact2 = 4, unload = 5;

integer tmpcs = 1;
reg [reg_width-1:0] mosi_d;
reg [reg_width-1:0] miso_d;
reg [counter_width:0] count;
reg [3:0] state;

reg [2:0] led_counter;

initial
    begin
        led_counter <= 0;   
        mosi_d <= 0;
        miso_d <= 0;
        state <= 0;
    end

always @(state)
    begin
        case (state)
          reset:
              begin
                miso_d <= 0;
                mosi_d <= 0;
                count <= 0;
                tmpcs <= 1;
              end
          idle:
              begin
                miso_d <= 0;
                mosi_d <= 0;
                count <= 0;
                tmpcs <= 1;
              end
          load:
              begin
                miso_d <= 0;
                mosi_d <= led;
                count <= reg_width;
                tmpcs <= 0;
              end
          transact1:
              begin
                tmpcs <= 0;
                miso_d <= {miso_d[reg_width-2:0], miso};
                mosi_d <= {mosi_d[reg_width-2:0], 1'b0};
                count <= count-1;
              end
          transact2:
              begin
                tmpcs <= 0;
                miso_d <= {miso_d[reg_width-2:0], miso};
                mosi_d <= {mosi_d[reg_width-2:0], 1'b0};
                count <= count-1;
              end
          unload:
              begin
                miso_d <= 0;
                mosi_d <= 0;
                count <= 0;
                tmpcs <= 1;
              end
          default:
              begin
                miso_d <= 0;
                mosi_d <= 0;
                count <= 0;
                tmpcs <= 1;
              end
       endcase
   end


  always @(posedge sys_clk)
  begin
    if (!rstn)
      state = reset;
    else
      case (state)
        reset:
          if (!t_start)
            state = load;
          else
            state = idle;
        idle:
          if (!t_start)
            state = load;
        load:
          if (count != 0)
            state = transact1;
          else
            state = reset;
        transact1:
          if (count != 0)
            state = transact2;
          else
            state = unload;
        transact2:
          if (count != 0)
            state = transact1;
          else
            state = unload;
        unload:
          if (!t_start)
            state = load;
          else
            state = idle;
      endcase
  end

  assign cs = tmpcs;
  assign mosi = ( ~cs ) ? mosi_d[reg_width-1] : 1'bz;
  assign sclk = ( state == transact1 || state == transact2) ? sys_clk : 1'b0;

always @(posedge sys_clk)
begin
    if (!rstn)
    begin
        led_counter <= 0;
    end
    else
    begin
        if (!up)
            begin
                led_counter <= led_counter + 1;
                if (led_counter == 5)
                    begin
                        led_counter <= 0;
                    end
            end
    end
end

genvar i;
generate
  for (i = 0; i < 6; i = i + 1)
  begin
    assign led[i] = (rstn ? led_counter != i : 0);
  end
endgenerate

endmodule

src/runner_tb.v
`timescale 1ns / 1ps

module runner_tb();

// Объявление регистров и проводов для подключения к модулю
reg rstn;                // Сигнал сброса
reg sys_clk;             // Тактовый сигнал
reg t_start;             // Сигнал запуска передачи
reg up;                  // Сигнал для увеличения счетчика
wire [5:0] led;         // Выходные светодиоды
wire cs;                // Сигнал выбора устройства
reg miso;               // Данные на входе (Master In Slave Out)
wire mosi;              // Данные на выходе (Master Out Slave In)
wire sclk;              // Тактовый сигнал SPI

// Экземпляр модуля SPI
runner master (
    .led(led),
    .rstn(rstn),
    .sys_clk(sys_clk),
    .t_start(t_start),
    .up(up),
    .cs(cs),
    .miso(miso),
    .mosi(mosi),
    .sclk(sclk)
);

// Генерация тактового сигнала
initial begin
    sys_clk = 0;
    forever #5 sys_clk = ~sys_clk; // Тактовая частота 100 МГц
end

// Процесс тестирования
initial begin
    // Инициализация сигналов
    rstn = 0; // Активный сброс
    t_start = 1;
    up = 1;
    miso = 0; // Изначально данные на входе равны 0

    // Сброс модуля
    #10;
    rstn = 1; // Снятие сброса
    #10;
    up = 0;
    #10; 
    up = 1;

    // Тест 1: Запуск передачи
    t_start = 0; // Запуск передачи
    #10;
    t_start = 1;

    // Завершение симуляции
    #100;
    $stop; // Останавливаем симуляцию
end

    initial begin
        $dumpfile("./runner_out.vcd");  // Файл для сохранения результатов
        $dumpvars(0, runner_tb);       // Сохраняем переменные для анализа
        #1000 $finish;                 // Завершаем симуляцию через 1000 ns
    end
    // Конец
endmodule


//`timescale 1ns / 1ps

//module runner_tb();

   //Parameters
//  parameter reg_width = 8;
//  
   //Testbench signals
//  reg rstn;
//  reg sys_clk;
//  reg cs;
//  reg mosi;
//  wire [5:0] led;

   //Instantiate the SPI slave module
//  runner_lab #(
//    .reg_width(reg_width)
//  ) uut (
//    .led(led),
//    .rstn(rstn),
//    .sys_clk(sys_clk),
//    .cs(cs),
//    .mosi(mosi),
//    .sclk() // sclk not used in testbench
//  );
//  
//  reg [7:0] _mosi;

   //Clock generation
//  initial begin
//    sys_clk = 0;
//    forever #5 sys_clk = ~sys_clk; // 10ns clock period
//  end

   //Test sequence
//  initial begin
     //Initialize signals
//    rstn = 0;
//    cs = 1;
//    mosi = 0;

     //Reset the module
//    #10;
//    rstn = 1; // Release reset
//    #10;

     //Start SPI transaction
//    cs = 0; // Activate chip select
//    _mosi = 8'b00101010; // Sample data to send

     //Send data bit by bit
//      mosi = _mosi[0]; // Assign the next bit of data
//      #5; // Wait for the clock edge
//      mosi = _mosi[1]; // Assign the next bit of data
//      #5; // Wait for the clock edge
//      mosi = _mosi[2]; // Assign the next bit of data
//      #5; // Wait for the clock edge
//      mosi = _mosi[3]; // Assign the next bit of data
//      #5; // Wait for the clock edge
//      mosi = _mosi[4]; // Assign the next bit of data
//      #5; // Wait for the clock edge
//      mosi = _mosi[5]; // Assign the next bit of data
//      #5; // Wait for the clock edge
//      mosi = _mosi[6]; // Assign the next bit of data
//      #5; // Wait for the clock edge
//      mosi = _mosi[7]; // Assign the next bit of data
//      #5; // Wait for the clock edge

     //Deactivate chip select
//    cs = 1;
//    #10;

     //Check the LED outputs
//    if (led != 6'b101010) // Expected output for mosi_d = 8'b101010
//      $display("Test failed: led = %b, expected led = 101010", led);
//    else
//      $display("Test passed: led = %b", led);

     //Finish simulation
//    #1000;
//    $finish;
//end

//initial begin
//        $dumpfile("./runner_out.vcd");  // Файл для сохранения результатов
//        $dumpvars(0, runner_tb);       // Сохраняем переменные для анализа
//        #1000 $finish;                 // Завершаем симуляцию через 1000 ns
//    end

//endmodule

runner_out.vcd
$date
	Thu Nov 21 16:49:46 2024
$end
$version
	Icarus Verilog
$end
$timescale
	1ps
$end
$scope module runner_tb $end
$var wire 1 ! sclk $end
$var wire 1 " mosi $end
$var wire 6 # led [5:0] $end
$var wire 1 $ cs $end
$var reg 1 % miso $end
$var reg 1 & rstn $end
$var reg 1 ' sys_clk $end
$var reg 1 ( t_start $end
$var reg 1 ) up $end
$scope module master $end
$var wire 1 % miso $end
$var wire 1 & rstn $end
$var wire 1 ' sys_clk $end
$var wire 1 ( t_start $end
$var wire 1 ) up $end
$var wire 1 ! sclk $end
$var wire 1 " mosi $end
$var wire 6 * led [5:0] $end
$var wire 1 $ cs $end
$var parameter 32 + counter_width $end
$var parameter 32 , idle $end
$var parameter 32 - load $end
$var parameter 32 . reg_width $end
$var parameter 32 / reset $end
$var parameter 32 0 transact1 $end
$var parameter 32 1 transact2 $end
$var parameter 32 2 unload $end
$var reg 4 3 count [3:0] $end
$var reg 3 4 led_counter [2:0] $end
$var reg 8 5 miso_d [7:0] $end
$var reg 8 6 mosi_d [7:0] $end
$var reg 4 7 state [3:0] $end
$var integer 32 8 tmpcs [31:0] $end
$scope begin genblk1[0] $end
$var parameter 2 9 i $end
$upscope $end
$scope begin genblk1[1] $end
$var parameter 2 : i $end
$upscope $end
$scope begin genblk1[2] $end
$var parameter 3 ; i $end
$upscope $end
$scope begin genblk1[3] $end
$var parameter 3 < i $end
$upscope $end
$scope begin genblk1[4] $end
$var parameter 4 = i $end
$upscope $end
$scope begin genblk1[5] $end
$var parameter 4 > i $end
$upscope $end
$upscope $end
$upscope $end
$enddefinitions $end
$comment Show the parameter values. $end
$dumpall
b101 >
b100 =
b11 <
b10 ;
b1 :
b0 9
b101 2
b100 1
b11 0
b0 /
b1000 .
b10 -
b1 ,
b11 +
$end
#0
$dumpvars
b1 8
b0 7
b0 6
b0 5
b0 4
b0 3
b0 *
1)
1(
0'
0&
0%
1$
b0 #
z"
0!
$end
#5000
1'
#10000
b111110 #
b111110 *
0'
1&
#15000
b1 7
1'
#20000
0'
0)
#25000
b111101 #
b111101 *
b1 4
1'
#30000
0'
0(
1)
#35000
0"
0$
b0 8
b1000 3
b111101 6
b10 7
1'
#40000
0'
1(
#45000
b111 3
b1111010 6
1!
b11 7
1'
#50000
0!
0'
#55000
1"
b110 3
b11110100 6
b100 7
1!
1'
#60000
0!
0'
#65000
b101 3
b11101000 6
b11 7
1!
1'
#70000
0!
0'
#75000
b100 3
b11010000 6
b100 7
1!
1'
#80000
0!
0'
#85000
b11 3
b10100000 6
b11 7
1!
1'
#90000
0!
0'
#95000
0"
b10 3
b1000000 6
b100 7
1!
1'
#100000
0!
0'
#105000
1"
b1 3
b10000000 6
b11 7
1!
1'
#110000
0!
0'
#115000
0"
b0 3
b0 6
b100 7
1!
1'
#120000
0!
0'
#125000
z"
1$
b1 8
b101 7
0!
1'
#130000
0'
#135000
b1 7
1'
