src/runner_lab.v
module runner_lab (
    output [5:0] led,
    input rstn,
    input sys_clk,
    input cs,
    input mosi,
    input sclk
);

parameter reg_width = 8;
parameter counter_width = $clog2(reg_width);
parameter reset = 0;
parameter idle = 1;
parameter load = 2;
parameter transact1 = 3;

reg [reg_width - 1:0] mosi_d;
reg [counter_width:0] count;
reg [3:0] state;

initial begin
    mosi_d <= 0;
    state <= reset;
end

always @(posedge sys_clk or negedge rstn) begin
    if (!rstn)
        state <= reset;
    else if (!cs) begin
        if (state == reset)
            state <= load;
        else if (state == load)
            state <= transact1;
    end else
        state <= idle;
end

always @(posedge sclk) begin
    if (!cs && state == transact1) begin
        mosi_d <= {mosi_d[reg_width - 2:0], mosi};
        count <= count - 1;
    end
end

genvar i;
generate
    for (i = 0; i < 6; i = i + 1) begin
        assign led[i] = (rstn ? mosi_d[7 - i] : 1);
    end
endgenerate

endmodule

src/runner.v
// Отправитель
// cd C:\iverilog\runner
// iverilog -o ./compiled ./src/runner.v ./src/runner_tb.v ./src/runner_lab.v
// vvp ./compiled 
// Модуль ведущего (Master)
module runner (
    output [5:0] led,
    input rstn,
    input sys_clk,
    input t_star,
    input up,
    input miso,
    output mosi,
    output sclk
);

parameter reg_width = 8;
parameter counter_width = $clog2(reg_width);
parameter reset = 0;
parameter idle = 1;
parameter load = 2;
parameter transact1 = 3;
parameter transact2 = 4;

reg [reg_width - 1:0] mosi_d;
reg [counter_width:0] count;
reg [3:0] state;
reg [2:0] led_counter;
reg tmpcs = 1;

initial begin
    led_counter <= 0;
    mosi_d <= 0;
    state <= reset;
end

always @(state) begin
    case (state)
        reset: begin
            mosi_d <= 0;
            count <= 0;
            tmpcs <= 1;
        end
        idle: begin
            mosi_d <= 0;
            count <= 0;
            tmpcs <= 1;
        end
        load: begin
            mosi_d <= led;
            count <= reg_width;
            tmpcs <= 0;
        end
        transact1: begin
            tmpcs <= 0;
            mosi_d <= {mosi_d[reg_width - 2:0], 1'b0};
            count <= count - 1;
        end
    endcase
end

assign mosi = (~tmpcs) ? mosi_d[reg_width - 1] : 1'bz;
assign sclk = (state == transact1 || state == transact2) ? sys_clk : 1'b0;

always @(posedge sys_clk) begin
    if (!rstn)
        led_counter <= 0;
    else if (!up) begin
        led_counter <= led_counter + 1;
        if (led_counter == 5)
            led_counter <= 0;
    end
end

genvar i;
generate
    for (i = 0; i < 6; i = i + 1) begin
        assign led[i] = (rstn ? led_counter != i : 0);
    end
endgenerate

endmodule

src/runner_tb.v
`timescale 1ns / 1ps

module runner_tb;
    // Регистры и провода для тестбенча
    reg sys_clk = 0;
    reg rstn = 0;
    reg t_start = 1;
    reg up = 1;
    reg cs = 1;
    reg [7:0] _mosi;  // Данные для передачи
    wire sclk;
    wire miso;
    wire mosi;  // Определяем как wire
    reg mosi_driver;  // Регистратор для управления mosi в тестбенче

    // Подключение модулей
    runner master (
        .led(),
        .rstn(rstn),
        .sys_clk(sys_clk),
        .t_star(t_start),
        .up(up),
        .mosi(mosi),  // Подключаем как wire
        .miso(miso),
        .sclk(sclk)
    );

    runner_lab slave (
        .led(),
        .rstn(rstn),
        .sys_clk(sys_clk),
        .cs(cs),
        .mosi(mosi),
        .sclk(sclk)
    );

    // Управляем mosi через непрерывное назначение
    assign mosi = mosi_driver;

    // Генерация системного тактового сигнала
    always #5 sys_clk = ~sys_clk;

    // Начало
    // Блок инициализации сигналов и начальных условий
    initial begin
        rstn = 0;  // Активный сброс
        t_start = 1;
        up = 1;
        cs = 1;
        mosi_driver = 0;

        // Этап 1: Сброс системы
        #10;
        rstn = 1;  // Выход из сброса
        #20;

        // Этап 2: Передача данных с мастера на ведомый
        t_start = 0;  // Начало передачи
        _mosi = 8'b11001010;  // Данные для передачи

        // Передача данных бит за битом
        repeat (8) begin
            #5 mosi_driver = _mosi[0];
            _mosi = _mosi >> 1;  // Сдвиг на 1 бит вправо
            #5;
        end

        // Этап 3: Завершение передачи
        t_start = 1;
        cs = 1;
        #10;

        // Этап 4: Тест работы кнопки `up`
        up = 0;  // Имитируем нажатие
        #10;
        up = 1;
        #50;
    end
    // Конец

    // Конец - обязательная часть
    initial begin
        $dumpfile("./runner_out.vcd");  // Файл для сохранения результатов
        $dumpvars(0, runner_tb);       // Сохраняем переменные для анализа
        #500 $finish;                  // Завершаем симуляцию через 500 ns
    end
    // Конец
endmodule

runner_out.vcd
$date
	Wed Nov 20 11:29:14 2024
$end
$version
	Icarus Verilog
$end
$timescale
	1ps
$end
$scope module runner_tb $end
$var wire 1 ! miso $end
$var wire 1 " mosi $end
$var wire 1 # sclk $end
$var reg 8 $ _mosi [7:0] $end
$var reg 1 % cs $end
$var reg 1 & mosi_driver $end
$var reg 1 ' rstn $end
$var reg 1 ( sys_clk $end
$var reg 1 ) t_start $end
$var reg 1 * up $end
$scope module master $end
$var wire 1 ! miso $end
$var wire 1 " mosi $end
$var wire 1 ' rstn $end
$var wire 1 ( sys_clk $end
$var wire 1 ) t_star $end
$var wire 1 * up $end
$var wire 1 # sclk $end
$var wire 6 + led [5:0] $end
$var parameter 32 , counter_width $end
$var parameter 32 - idle $end
$var parameter 32 . load $end
$var parameter 32 / reg_width $end
$var parameter 32 0 reset $end
$var parameter 32 1 transact1 $end
$var parameter 32 2 transact2 $end
$var reg 4 3 count [3:0] $end
$var reg 3 4 led_counter [2:0] $end
$var reg 8 5 mosi_d [7:0] $end
$var reg 4 6 state [3:0] $end
$var reg 1 7 tmpcs $end
$scope begin genblk1[0] $end
$var parameter 2 8 i $end
$upscope $end
$scope begin genblk1[1] $end
$var parameter 2 9 i $end
$upscope $end
$scope begin genblk1[2] $end
$var parameter 3 : i $end
$upscope $end
$scope begin genblk1[3] $end
$var parameter 3 ; i $end
$upscope $end
$scope begin genblk1[4] $end
$var parameter 4 < i $end
$upscope $end
$scope begin genblk1[5] $end
$var parameter 4 = i $end
$upscope $end
$upscope $end
$scope module slave $end
$var wire 1 % cs $end
$var wire 1 " mosi $end
$var wire 1 ' rstn $end
$var wire 1 # sclk $end
$var wire 1 ( sys_clk $end
$var wire 6 > led [5:0] $end
$var parameter 32 ? counter_width $end
$var parameter 32 @ idle $end
$var parameter 32 A load $end
$var parameter 32 B reg_width $end
$var parameter 32 C reset $end
$var parameter 32 D transact1 $end
$var reg 4 E count [3:0] $end
$var reg 8 F mosi_d [7:0] $end
$var reg 4 G state [3:0] $end
$scope begin genblk1[0] $end
$var parameter 2 H i $end
$upscope $end
$scope begin genblk1[1] $end
$var parameter 2 I i $end
$upscope $end
$scope begin genblk1[2] $end
$var parameter 3 J i $end
$upscope $end
$scope begin genblk1[3] $end
$var parameter 3 K i $end
$upscope $end
$scope begin genblk1[4] $end
$var parameter 4 L i $end
$upscope $end
$scope begin genblk1[5] $end
$var parameter 4 M i $end
$upscope $end
$upscope $end
$upscope $end
$enddefinitions $end
$comment Show the parameter values. $end
$dumpall
b101 M
b100 L
b11 K
b10 J
b1 I
b0 H
b11 D
b0 C
b1000 B
b10 A
b1 @
b11 ?
b101 =
b100 <
b11 ;
b10 :
b1 9
b0 8
b100 2
b11 1
b0 0
b1000 /
b10 .
b1 -
b11 ,
$end
#0
$dumpvars
b0 G
b0 F
bx E
b111111 >
17
b0 6
b0 5
b0 4
b0 3
b0 +
1*
1)
0(
0'
0&
1%
bx $
0#
0"
z!
$end
#5000
1(
#10000
b0 >
b111110 +
0(
1'
#15000
b1 G
1(
#20000
0(
#25000
1(
#30000
0(
b11001010 $
0)
#35000
1(
b1100101 $
#40000
0(
#45000
1(
b110010 $
1"
1&
#50000
0(
#55000
1(
b11001 $
0"
0&
#60000
0(
#65000
1(
b1100 $
1"
1&
#70000
0(
#75000
1(
b110 $
0"
0&
#80000
0(
#85000
1(
b11 $
#90000
0(
#95000
1(
b1 $
1"
1&
#100000
0(
#105000
1(
b0 $
#110000
0(
1)
#115000
1(
#120000
0(
0*
#125000
b111101 +
b1 4
1(
#130000
0(
1*
